<templateSet group="plain">
  <template name="st" value="String " description="String" toReformat="false" toShortenFQNames="true">
    <context>
      <option name="GROOVY_DECLARATION" value="true" />
      <option name="GROOVY_EXPRESSION" value="true" />
      <option name="GROOVY_STATEMENT" value="true" />
      <option name="JAVA_DECLARATION" value="true" />
      <option name="JAVA_EXPRESSION" value="true" />
      <option name="JAVA_STATEMENT" value="true" />
    </context>
  </template>
  <template name="puf" value="public final" description="public final" toReformat="false" toShortenFQNames="true">
    <context>
      <option name="JAVA_DECLARATION" value="true" />
    </context>
  </template>
  <template name="psf" value="private static final " description="private static final" toReformat="false" toShortenFQNames="false" />
  <template name="pusf" value="public static final " description="public static final" toReformat="false" toShortenFQNames="false">
    <context>
      <option name="GROOVY_DECLARATION" value="true" />
      <option name="JAVA_DECLARATION" value="true" />
    </context>
  </template>
  <template name="psfs" value="private static final String " description="private static final String" toReformat="false" toShortenFQNames="false" />
  <template name="psfi" value="private static final int " description="private static final int" toReformat="false" toShortenFQNames="false" />
  <template name="pf" value="private final " description="private final" toReformat="false" toShortenFQNames="true">
    <context>
      <option name="JAVA_DECLARATION" value="true" />
    </context>
  </template>
</templateSet>